<?xml version="1.0" encoding="UTF-8" ?>
<request xmlns="http://www.isinet.com/xrpc41"
src="app.id=VIVOHarvester,env.id=Ubuntu Linux,partner.email=jrpence@ctrip.ufl.edu">
	<fn name="LinksAMR.retrieve">
		<list>
	<!-- WHO'S REQUESTING -->
		<map>
			<!-- <val name="username">username</val>
			<val name="password">test</val> -->
		</map>
	<!-- WHAT'S REQUESTED -->
		<map>
			<list name="WOS">
				<val>timesCited</val>
				<val>ut</val>
				<val>doi</val>
				<val>sourceURL</val>
				<val>citingArticlesURL</val>
				<val>relatedRecordsURL</val>
			</list>
		</map> <!--end "return_data" -->
	<!-- LOOKUP DATA 
		       leave "lookup" as the id of the map. It is used by WOSFetch to identify this location-->
		<map id="lookup">
		<!-- QUERY "doc1"  -->
		<!--  <map name="doc1">
			<val name="ut">000178501400067</val>
		</map> --> <!-- end of doc1-->
		
		</map> <!-- end of citations -->
		</list>
	</fn>
</request>
	