<?xml version="1.0" encoding="UTF-8"?>
<!--
  Copyright (c) 2010-2011 VIVO Harvester Team. For full list of contributors, please see the AUTHORS file provided.
  All rights reserved.
  This program and the accompanying materials are made available under the terms of the new BSD license which accompanies this distribution, and is available at http://www.opensource.org/licenses/bsd-license.html
-->
<config>
    # harvesting publications from TIB – Leibniz Information Centre for Science and Technology. exchange the ROR ID to test with your institution.
    <param name="file">https://api.openalex.org/works?filter=authorships.institutions.ror:https://ror.org/04aj4c181&amp;per-page=200&amp;mailto=forschungsatlas@tib.eu&amp;cursor=*</param>

    # harvesting of publications from the subfield "Semantic Web and Ontology Develoment", should result in ca. 9-10k publications
<!--    <param name="file">https://api.openalex.org/works?page=1&filter=primary_topic.id:t10215,publication_year:2022-2024&amp;per-page=200&amp;cursor=*</param>-->

    # harvesting of publications from the journal "Quantitative Science Studies".
<!--    <param name="file">https://api.openalex.org/works?page=1&filter=primary_location.source.id:s4210195326&amp;per-page=200&amp;mailto=forschungsatlas@tib.eu&amp;cursor=*</param>-->

    <param name="output">raw-records.config.xml</param>
    <param name="namespaceBase">http://vivo.example.com/harvest/aims_users/</param>
    <param name="description">publication</param>
    <param name="id">uid</param>
    <param name="path">$.results</param>
    <Param name="wordiness">INFO</Param>
</config>

